revoregex/__init__.py
revoregex/matcher.py
revoregex-0.1.0.dist-info/licenses/LICENSE
revoregex-0.1.0.dist-info/METADATA
revoregex-0.1.0.dist-info/WHEEL
revoregex-0.1.0.dist-info/top_level.txt
revoregex-0.1.0.dist-info/RECORD
