Metadata-Version: 2.4
Name: revoregex
Version: 0.1.0
Summary: A multilingual regex library for Python (Turkish, English, German, French, and more)
Author: Barış Aksel
Author-email: iletisim@barisaksel.com
Project-URL: Source, https://github.com/Barisaksel/RevoRegex
Project-URL: Bug Tracker, https://github.com/Barisaksel/RevoRegex/issues
Keywords: regex validation multilingual i18n internationalization Turkish English German French IBAN credit-card phone email domain python luhn mod97 json html uuid mac plate password username open-source PyPI form-validation data-validation
Classifier: Programming Language :: Python :: 3
Classifier: License :: OSI Approved :: MIT License
Classifier: Operating System :: OS Independent
Classifier: Natural Language :: Turkish
Classifier: Natural Language :: English
Classifier: Natural Language :: German
Classifier: Natural Language :: French
Classifier: Topic :: Software Development :: Libraries :: Python Modules
Classifier: Intended Audience :: Developers
Classifier: Development Status :: 4 - Beta
Requires-Python: >=3.7
License-File: LICENSE
Dynamic: author
Dynamic: author-email
Dynamic: classifier
Dynamic: description
Dynamic: description-content-type
Dynamic: keywords
Dynamic: license-file
Dynamic: project-url
Dynamic: requires-python
Dynamic: summary
